admin/__init__.py
winadmin32-1.0.dist-info/LICENSE
winadmin32-1.0.dist-info/METADATA
winadmin32-1.0.dist-info/WHEEL
winadmin32-1.0.dist-info/top_level.txt
winadmin32-1.0.dist-info/RECORD
